{
  "series": "Request for Comments",
  "number": "12",
  "howpublished": "RFC 12",
  "publisher": "RFC Editor",
  "doi": "10.17487/RFC0012",
  "url": "https://www.rfc-editor.org/info/rfc12",
  "title": "IMP-Host interface flow diagrams",
  "pagetotal": "1",
  "year": "1969",
  "month": "aug",
  "body": "\n\n\n\n\n\nNetwork Working Group                                       M. Wingfield\nRequest for Comments: 12  REVISED                         26 August 1969\n\n\n                    IMP-HOST INTERFACE FLOW DIAGRAMS\n\n   The following flow diagrams were extracted from the logic diagrams\n   provided in Appendix B of BBN Report No. 1822.  These diagrams\n   indicate the logical sequence of hardware operations which occur\n   within the IMP-HOST interface.  The logic names appearing in the\n   blocks correspond to the logic elements found in Appendix B.\n\n\n\n\n\n\n\n\n\n\n\n\n\n\n\n\n\n\n\n\n\n\n\n\n\n\n\n\n\n\n\n\n\n\n\n\n\n\n\n\nWingfield                                                       [Page 1]\n\f\nRFC 12              IMP-HOST INTERFACE FLOW DIAGRAMS      26 August 1969\n\n\nIMP to HOST Message\n                       +----------+\n                       |  Start   |\n                       |  Input   |\n                       +----------+\n                             |\n                             V\n                 +------------------------+\n                 | LAST \u003c--0; IMPERR \u003c--0 |\n                 | PAD \u003c--0; IN REQST \u003c--0|\n                 |  COUNTER \u003c--0          |\n                 +------------------------+      +---+\n                             |\u003c----------------- | B |\n                             V                   +---+\n                      +--------------+\n                      | RFNIB \u003c-- 1  |\n                      +--------------+\n                             |\u003c--------------+\n                             V               |\n                            / \\              |\n                          /     \\            |\n                        / THERE'S \\ N        |\n                        \\YOUR BIT /----------+\n                          \\=1 ? /\n                            \\ /\n                             |\n        +-------------------\u003eV\n        |                   / \\\n   +----+------+    N     /     \\\n   | IMP ERROR |\u003c------ /   IMP   \\\n   | \u003c--- 1    |        \\  READY  /\n   +-----------+          \\ ?   /\n                            \\ /\n                             | Y\n                             V\n                            / \\\n                          /     \\\n   +-----------+   Y    /  LAST   \\\n   | PAD \u003c-- 1 |\u003c-------\\ IMP BIT /\n   +-----------+          \\ =1? /\n        |                   \\ /                 +---+\n        +-------------------\u003e|\u003c-----------------| C |\n                             V                  +---+\n                +-----------------------+\n                |    PULSE SHIFT REG.   |       +---+\n                |   INCREMENT COUNTER   |------\u003e| A |\n                |      RFNTR \u003c-- 0      |       +---+\n                +-----------------------+\n\n\n\nWingfield                                                       [Page 2]\n\f\nRFC 12              IMP-HOST INTERFACE FLOW DIAGRAMS      26 August 1969\n\n\n      +---+                +---+\n      | C |                | A |\n      +-+-+                +-+-+\n        ^                    |\n        | Y                  V\n       / \\                  / \\\n     /     \\          N   /WORD \\\n   /  PAD=1  \\ \u003c--------/ LENGTH  \\\n   \\    ?    /          \\   =1    /\n     \\     /              \\  ?  /\n       \\ /                  \\ /\n        | N                  |\n        V                    V\n      +---+       +----------------------+\n      | B |       |     INREQST \u003c--1     |\n      +---+       +----------------------+\n                             |\u003c-----------+\n                             V            |\n                            / \\           |\n                          /DATA \\         |\n                        /HAS BEEN \\_N_____|\n                        \\ TAKEN   /\n                          \\ ?   /\n                            \\ /\n                             V Y\n                  +----------------------+\n                  |    INREQST \u003c--0      |\n                  +----------------------+\n                             V\n                            / \\\n                          /     \\              +------------+\n                        / LAST = 1\\-----------\u003e|   END  OF  |\n                        \\    ?    /            |   MESSAGE  |\n                          \\     /              +------------+\n                            \\ /                       ^\n                             | N                      |\n                             V                        |\n                            / \\                       |\n                          /     \\                     |\n                        / PAD = 1 \\-------------------+\n                        \\     ?   /\n                          \\     /\n                            \\ /\n                             | N\n                             V\n   +---+          +---------------------+\n   | B |\u003c---------|    CLEAR COUNTER    |\n   +---+          +---------------------+\n\n\n\nWingfield                                                       [Page 3]\n\f\nRFC 12              IMP-HOST INTERFACE FLOW DIAGRAMS      26 August 1969\n\n\nHOST TO IMP MESSAGE\n\n            +--------------+\n            | START OUTPUT |\n            +------+-------+\n                   V\n       +------------------------+\n       | COUNTER \u003c-- 1          |\n       | LSTWD \u003c--0; BTAVL \u003c--0 |\n       +-----------+------------+        +---+\n                   |\u003c--------------------| C |\n                   V                     +---+\n       +-----------+------------+\n       |    OUT REQST \u003c-- 1     |\n       |     CLEAR SHIFT REG.   |\n       +-----------+------------+\n     +------------\u003e|\n     |             V\n     |            / \\\n     |      N   /     \\\n     |_______ / STROBE  \\\n              \\DATA WORD/\n                \\ =1 ?/\n                  \\ /\n                   V  Y\n      +------------+------------+\n      |  LOAD SHIFT  REGISTER   |\n      |  OUTREQST \u003c-- 0         |\n      |  COUNTER  \u003c-- 1         |\n      +-------------------------+\n      +----------\u003e|\n      |           V\n      |          / \\\n      |        /     \\\n      |N     / RFNBIT  \\\n      +----- \\   = 1   /\n               \\   ? /            +----------+\n                 \\ /              |          | N\n                  V   Y           |         / \\\n         +--------+--------+      V       /     \\\n         |  THERE'S YOUR   |-----------\u003e/ RFNBIT  \\\n         | HOST BET \u003c-- 1  |            \\  = 0    /\n         +-----------------+              \\  ?  /\n                                            \\ /\n                                             | Y\n                                           +-+-+\n                                           | A |\n                                           +---+\n\n\n\nWingfield                                                       [Page 4]\n\f\nRFC 12              IMP-HOST INTERFACE FLOW DIAGRAMS      26 August 1969\n\n\n                               +---+\n                               | A |\n                               +---+\n                                 V\n                  +--------------+-------------+\n                  | THERE'S YOUR HOST BIT \u003c--0 |\n                  |      BTAVL \u003c-- 0           |\n                  +----------------------------+\n                                 V\n                                / \\                   / \\\n                              / WORD\\   Y           /     \\   Y\n                            /LENGTH -1\\----------\u003e/  LSTWD  \\---+\n                            \\   = 1   /           \\   = 1   /   |\n                              \\  ?  /               \\  ?  /     |\n                                \\ /                   \\ /       |\n                                 | N                   | N      |\n                                 V                     |        |\n                                / \\                    |        |\n                              / WORD\\                  |        V\n           ________________ / LENGTH  \\                |  +------------+\n           |                \\  = 1    /                |  | LIBIT \u003c- 1 |\n           |                  \\  ?  /                  |  +------------+\n           |                    \\ /                    V        |\n           |                     |\u003c-----------------------\u003c------+\n           |                     V\n           |            +-----------------+\n           |            | PUSH SHIFT REG. |\n    +-------------+     |INCREMENT COUNTER|\n    | LIBIT \u003c-- 0 |     +-----------------+\n    +-------------+              V\n           |                   +---+\n           |                   | B |\n           V                   +---+\n          / \\\n        /     \\\n      /  LSTWD  \\ Y                          +-------------+\n      \\   = 1   /---------------------------\u003e|   END OF    |\n        \\  ?  /                              |   MESSAGE   |\n          \\ /                                +-------------+\n           | N\n           V\n         +---+\n         | C |\n         +---+\n\n\n         [ This RFC was put into machine readable form for entry ]\n             [ into the online RFC archives by Lorrie Shiota]\n\n\n\nWingfield                                                       [Page 5]\n\f\nRFC 12              IMP-HOST INTERFACE FLOW DIAGRAMS      26 August 1969\n\n\n\n\n\n\n\n\n\n\n\n\n\n\n\n\n\n\n\n\n\n\n\n\n\n\n\n\n\n\n\n\n\n\n\n\n\n\n\n\n\n\n\n\n\n\n\n\n\n\n\n\n\nWingfield                                                       [Page 6]\n\f\n"
}